{
  "kind": "docker::Image",
  "id": "gateway-image",
  "fqn": "origan-infrastructure/achanger/gateway-image",
  "seq": 19,
  "data": {},
  "status": "updated",
  "output": {
    "Symbol(alchemy::ResourceKind)": "docker::Image",
    "Symbol(alchemy::ResourceID)": "gateway-image",
    "Symbol(alchemy::ResourceFQN)": "origan-infrastructure/achanger/gateway-image",
    "Symbol(alchemy::ResourceScope)": {
      "@scope": null
    },
    "Symbol(alchemy::ResourceSeq)": 19,
    "registryUrl": "registry.platform.origan.dev",
    "imageName": "gateway",
    "tag": "1757630151062",
    "context": "../",
    "dockerfile": "build/docker/prod.Dockerfile",
    "target": "gateway",
    "platforms": [
      "linux/amd64"
    ],
    "buildArgs": {
      "NODE_ENV": "production",
      "BUILD_VERSION": "1757630151062"
    },
    "push": true,
    "fullImageUrl": "registry.platform.origan.dev/gateway:1757630151062",
    "digest": "sha256:6f3a660b3359260b9620e013301394a38c0e65f5982979063eb2648e2c360791"
  },
  "props": {
    "registryUrl": "registry.platform.origan.dev",
    "imageName": "gateway",
    "tag": "1757630151062",
    "context": "../",
    "dockerfile": "build/docker/prod.Dockerfile",
    "target": "gateway",
    "platforms": [
      "linux/amd64"
    ],
    "buildArgs": {
      "NODE_ENV": "production",
      "BUILD_VERSION": "1757630151062"
    },
    "push": true
  }
}